{
  "uid": "workflow_action",
  "type": "workflow-action",
  "config": {
    "actionUrl": "https://kwtsms-hubspot-backend.example.com/api/workflow-action/send-sms",
    "isPublished": true,
    "supportedClients": [
      {
        "client": "WORKFLOWS"
      }
    ],
    "inputFields": [
      {
        "typeDefinition": {
          "name": "phone_property",
          "type": "enumeration",
          "fieldType": "select",
          "options": [
            { "value": "phone", "label": "Phone number" },
            { "value": "mobilephone", "label": "Mobile phone number" }
          ]
        },
        "supportedValueTypes": ["STATIC_VALUE"],
        "isRequired": true
      },
      {
        "typeDefinition": {
          "name": "message",
          "type": "string",
          "fieldType": "textarea"
        },
        "supportedValueTypes": ["STATIC_VALUE"],
        "isRequired": true
      },
      {
        "typeDefinition": {
          "name": "sender_id",
          "type": "string",
          "fieldType": "text"
        },
        "supportedValueTypes": ["STATIC_VALUE"],
        "isRequired": true
      }
    ],
    "labels": {
      "en": {
        "actionName": "Send SMS via kwtSMS",
        "actionDescription": "Send an SMS message to a contact using the kwtSMS gateway",
        "actionCardContent": "Send SMS to {{phone_property}}",
        "inputFieldLabels": {
          "phone_property": "Phone number property",
          "message": "Message",
          "sender_id": "Sender ID"
        },
        "inputFieldDescriptions": {
          "phone_property": "Select which contact property contains the phone number",
          "message": "The SMS message to send. Use personalization tokens like {{contact.firstname}}",
          "sender_id": "The sender ID to display on the recipient phone"
        }
      }
    },
    "objectTypes": ["CONTACT"]
  }
}
